disid/__init__.py
disid/disid.py
disid/keytools.py
disid-0.1.dist-info/LICENSE.md
disid-0.1.dist-info/METADATA
disid-0.1.dist-info/WHEEL
disid-0.1.dist-info/top_level.txt
disid-0.1.dist-info/RECORD
