Metadata-Version: 2.1
Name: disid
Version: 0.1
Summary: An Integer ID Disguiser to make your values look more professional.
Author-email: Asher Glick <aglick@aglick.com>
Project-URL: Homepage, https://github.com/AsherGlick/Disid
Project-URL: Issues, https://github.com/AsherGlick/Disid/issues
Classifier: Programming Language :: Python :: 3
Classifier: License :: OSI Approved :: BSD License
Classifier: Operating System :: OS Independent
License-File: LICENSE.md
